firevm/__init__.py
firevm/async_client.py
firevm/client.py
firevm/exceptions.py
firevm/http_client.py
firevm/models.py
firevm/resources/__init__.py
firevm/resources/api_keys.py
firevm/resources/vms.py
firevm-0.4.1.dist-info/licenses/LICENSE
firevm-0.4.1.dist-info/METADATA
firevm-0.4.1.dist-info/WHEEL
firevm-0.4.1.dist-info/top_level.txt
firevm-0.4.1.dist-info/RECORD
