Metadata-Version: 2.4
Name: firevm
Version: 0.4.1
Summary: Official Python SDK for FireVM - MicroVM Management Platform
Home-page: https://github.com/firevm/firevm-python
Author: FireVM Team
Author-email: FireVM Team <support@firevm.dev>
License: MIT
Project-URL: Homepage, https://firevm.dev
Project-URL: Documentation, https://docs.firevm.dev
Project-URL: Repository, https://github.com/firevm/firevm-python
Project-URL: Issues, https://github.com/firevm/firevm-python/issues
Keywords: firevm,microvm,firecracker,vm,cloud,infrastructure
Requires-Python: >=3.8
License-File: LICENSE
Requires-Dist: requests>=2.31.0
Requires-Dist: pydantic>=2.0.0
Provides-Extra: async
Requires-Dist: aiohttp>=3.9.0; extra == "async"
Provides-Extra: dev
Requires-Dist: pytest>=7.4.0; extra == "dev"
Requires-Dist: pytest-asyncio>=0.21.0; extra == "dev"
Requires-Dist: pytest-cov>=4.1.0; extra == "dev"
Requires-Dist: black>=23.0.0; extra == "dev"
Requires-Dist: mypy>=1.5.0; extra == "dev"
Requires-Dist: ruff>=0.1.0; extra == "dev"
Dynamic: author
Dynamic: home-page
Dynamic: license-file
Dynamic: requires-python
